setup.py
gmind/__init__.py
gmind.egg-info/PKG-INFO
gmind.egg-info/SOURCES.txt
gmind.egg-info/dependency_links.txt
gmind.egg-info/requires.txt
gmind.egg-info/top_level.txt